risk_modeling/__init__.py
risk_modeling/modeling_procedure.py
risk_modeling/modeling_tools.py
risk_modeling-1.0.0.dist-info/METADATA
risk_modeling-1.0.0.dist-info/WHEEL
risk_modeling-1.0.0.dist-info/top_level.txt
risk_modeling-1.0.0.dist-info/RECORD
