Metadata-Version: 2.4
Name: risk_modeling
Version: 1.0.0
Summary: ML modeling tools in python for risk management domain including loan, credit card, etc.
Author-email: Xin Zhang <749958200@qq.com>
License: MIT
Project-URL: Homepage, https://github.com/yourusername/my_package
Project-URL: Bug Tracker, https://github.com/yourusername/my_package/issues
Requires-Python: >=3.11
Requires-Dist: lightgbm==4.6.0
Requires-Dist: numpy==2.1.2
Requires-Dist: pandas==2.3.2
Requires-Dist: scikit-learn==1.7.2
Requires-Dist: xgboost==3.0.5
Requires-Dist: matplotlib==3.10.6
